ReadyCellOne/core.py
ReadyCellOne/init.py
ReadyCellOne/plot.py
ReadyCellOne/utils.py
ReadyCellOne-0.1.5.dist-info/METADATA
ReadyCellOne-0.1.5.dist-info/WHEEL
ReadyCellOne-0.1.5.dist-info/top_level.txt
ReadyCellOne-0.1.5.dist-info/RECORD
